{"data_mtime":1716406455,"dep_lines":[9,19,20,41,3,4,5,6,7,8,10,12,13,16,17,1,1,1,1,1,1,1,1,1,1,1,1,1,1,1,1,1,1,15,14],"dep_prios":[5,5,5,5,10,10,10,10,10,5,5,10,5,5,5,5,30,30,30,30,30,30,30,30,30,30,30,30,30,30,30,30,30,5,5],"dependencies":["importlib.metadata","su6.__about__","su6.core","su6.plugins","contextlib","math","os","sys","typing","dataclasses","json","typer","configuraptor","rich","typing_extensions","builtins","_collections_abc","_typeshed","abc","click","click.core","click.exceptions","configuraptor.abs","configuraptor.cls","configuraptor.singleton","enum","importlib","io","json.decoder","typer.core","typer.main","typer.models","types"],"hash":"67822f3f615a97bd6e700f5b46adf92ea4846c03ded7edcd84c481a56d8cf747","id":"su6.cli","ignore_all":false,"interface_hash":"587da68fcf863fac93ce771ee66a7d7aa39c3d0b51f617f2d5548b76016c4ae4","mtime":1716406538,"options":{"allow_redefinition":false,"allow_untyped_globals":false,"always_false":[],"always_true":[],"bazel":false,"check_untyped_defs":true,"disable_bytearray_promotion":false,"disable_error_code":[],"disable_memoryview_promotion":false,"disabled_error_codes":[],"disallow_any_decorated":false,"disallow_any_explicit":false,"disallow_any_expr":false,"disallow_any_generics":true,"disallow_any_unimported":false,"disallow_incomplete_defs":true,"disallow_subclassing_any":true,"disallow_untyped_calls":true,"disallow_untyped_decorators":true,"disallow_untyped_defs":true,"enable_error_code":[],"enabled_error_codes":[],"extra_checks":true,"follow_imports":"normal","follow_imports_for_stubs":false,"ignore_errors":false,"ignore_missing_imports":true,"implicit_optional":true,"implicit_reexport":false,"local_partial_types":false,"mypyc":false,"old_type_inference":false,"platform":"linux","plugins":[],"strict_concatenate":false,"strict_equality":true,"strict_optional":true,"warn_no_return":true,"warn_return_any":true,"warn_unreachable":false,"warn_unused_ignores":true},"path":"src/su6/cli.py","plugin_data":null,"size":15061,"suppressed":["plumbum.machines","plumbum"],"version_id":"1.10.0"}